Metadata-Version: 2.1
Name: responsive-http
Version: 0.0.2
Summary: Responsive-http supported for http response. Specialy, It's a part in Fullstack-MQTT platform
Author: Phuc Bao
Author-email: nguyentranphucbao.working@gmail.com
